Metadata-Version: 2.1
Name: datanexus
Version: 0.0.8
Summary: A dataset module for your projects
Author: Ethan Barr
Author-email: ethanwbarr07@gmail.com
